[
  { "question": "apple (n)\n/ˈæp.l̩/", "answer": "Quả táo" },
  { "question": "banana (n)\n/bəˈnɑː.nə/", "answer": "Quả chuối" },
  { "question": "pear (n)\n/peə/", "answer": "Quả lê" },
  { "question": "grape (n)\n/ɡreɪp/", "answer": "Quả nho" },
  { "question": "peach (n)\n/piːtʃ/", "answer": "Quả đào" },
  { "question": "orange (n)\n/ˈɒr.ɪndʒ/", "answer": "Quả cam" },
  { "question": "mango (n)\n/ˈmæŋ.ɡəʊ/", "answer": "Quả xoài" },
  { "question": "coconut (n)\n/ˈkəʊ.kə.nʌt/", "answer": "Quả dừa" },
  { "question": "pineapple (n)\n/ˈpaɪnˌæp.l̩/", "answer": "Quả dứa" },
  { "question": "watermelon (n)\n/ˈwɔː.təˌmel.ən/", "answer": "Quả dưa hấu" },
  { "question": "durian (n)\n/ˈdʊə.ri.ən/", "answer": "Quả sầu riêng" },
  { "question": "lychee (n)\n/ˈlaɪ.tʃiː/", "answer": "Quả vải" },
  { "question": "guava (n)\n/ˈɡwɑː.və/", "answer": "Quả ổi" },
  { "question": "starfruit (n)\n/ˈstɑː.fruːt/", "answer": "Quả khế" },
  { "question": "apricot (n)\n/ˈeɪ.prɪ.kɒt/", "answer": "Quả mơ" },
  { "question": "jackfruit (n)\n/ˈdʒæk.fruːt/", "answer": "Quả mít" },
  { "question": "avocado (n)\n/ˌæv.əˈkɑː.dəʊ/", "answer": "Quả bơ" },
  { "question": "papaya (n)\n/pəˈpaɪ.ə/", "answer": "Quả đu đủ" },
  { "question": "plum (n)\n/plʌm/", "answer": "Quả mận" },
  { "question": "lemon (n)\n/ˈlem.ən/", "answer": "Quả chanh vàng" },
  { "question": "kiwi (n)\n/ˈkiː.wiː/", "answer": "Quả kiwi" },
  { "question": "raspberry (n)\n/ˈrɑːz.bər.i/", "answer": "Quả mâm xôi" },
  { "question": "blueberry (n)\n/ˈbluː.bər.i/", "answer": "Quả việt quất" }
]
